sherpa_ncnn/__init__.py
sherpa_ncnn/recognizer.py
sherpa_ncnn/sherpa-ncnn.pc
sherpa_ncnn/lib/_sherpa_ncnn.cpython-311-arm-linux-gnueabihf.so
sherpa_ncnn/lib/libncnn.so
sherpa_ncnn-2.1.15.dist-info/LICENSE
sherpa_ncnn-2.1.15.dist-info/METADATA
sherpa_ncnn-2.1.15.dist-info/WHEEL
sherpa_ncnn-2.1.15.dist-info/top_level.txt
sherpa_ncnn-2.1.15.dist-info/RECORD
