Metadata-Version: 2.1
Name: sherpa-ncnn
Version: 2.1.15
Home-page: https://github.com/k2-fsa/sherpa-ncnn
Author: The sherpa-ncnn development team
Author-email: dpovey@gmail.com
License: Apache licensed, as found in the LICENSE file
Classifier: Programming Language :: C++
Classifier: Programming Language :: Python
Classifier: Topic :: Scientific/Engineering :: Artificial Intelligence
Requires-Python: >=3.7
License-File: LICENSE
Requires-Dist: numpy
